input_output_test/inst_rom.v
`timescale 1ns / 1ps

/*
**  COE181.1 Lab4/5 Provided Module
** -------------------------------------------------------------------
**  Instruction Rom for Single-Cycle MIPS Processor for Altera FPGAs
**
**
**
**  NOTE:  The Provided Modules do NOT follow the course coding standards
*/

module inst_rom (
	input	clock,
	input reset,
	input [31:0] addr_in,
	output [31:0] data_out
);
	parameter ADDR_WIDTH=8;
	parameter INIT_PROGRAM="blank.memh";

	reg [31:0] rom [0:2**ADDR_WIDTH-1];
	reg [31:0] out;
	
	assign data_out = {out[7:0],out[15:8],out[23:16],out[31:24]}; //flip bytes
	
	initial
	begin
		$readmemh(INIT_PROGRAM, rom);
	end
	
	always @(posedge clock) begin
		if (reset) begin
			out <= 32'h00000000;
		end else begin
			out <= rom[addr_in[ADDR_WIDTH+1:2]];
		end
	end

endmodule

input_output_test/inst_rom_tb.v
`include "inst_rom.v"

module inst_rom_tb();
    reg clk, rst;
    reg [31: 0] addr_in;
    wire[31:0] data_out;
    
    inst_rom instruction_memory(clk, rst, addr_in, data_out);

    always #1 clk = ~clk;

    initial begin 

        $dumpfile("inst_rom_tb.vcd");
        $dumpvars(0, inst_rom_tb);
        clk <= 0;
        rst <= 0;
        
        #1
        rst <= 1;

        #1
        rst <= 0;
        #1 addr_in <= 32'b00000000000000000000000000000000;
        #1 addr_in <= 32'b00000000000000000000000000000001;
        #1 addr_in <= 32'b00000000000000000000000000000010;
        #1 addr_in <= 32'b00000000000000000000000000000011;
        #1 addr_in <= 32'b00000000000000000000000000000100;
        // #1 addr_in <= 32'b00000000000000000000000000000101;
        // #1 addr_in <= 32'b00000000000000000000000000000110;
        // #1 addr_in <= 32'b00000000000000000000000000000111;
        // #1 addr_in <= 32'b00000000000000000000000000001000;
        // #1 addr_in <= 32'b00000000000000000000000000001001;
        // #1 addr_in <= 32'b00000000000000000000000000001010;
        // #1 addr_in <= 32'b00000000000000000000000000001011;
        // #1 addr_in <= 32'b00000000000000000000000000001100;
        // #1 addr_in <= 32'b00000000000000000000000000001101;
        // #1 addr_in <= 32'b00000000000000000000000000001110;
        // #1 addr_in <= 32'b00000000000000000000000000001111;
        // #1 addr_in <= 32'b00000000000000000000000000010000;
        $display("%b", data_out[5:0]);
        #15 $finish;
    end

endmodule

input_output_test/inst_rom_tb.vcd
$date
	Tue Dec 06 23:05:25 2022
$end
$version
	Icarus Verilog
$end
$timescale
	1ps
$end
$scope module inst_rom_tb $end
$var wire 32 ! data_out [31:0] $end
$var reg 32 " addr_in [31:0] $end
$var reg 1 # clk $end
$var reg 1 $ rst $end
$scope module instruction_memory $end
$var wire 32 % addr_in [31:0] $end
$var wire 1 # clock $end
$var wire 1 $ reset $end
$var wire 32 & data_out [31:0] $end
$var reg 32 ' out [31:0] $end
$upscope $end
$upscope $end
$enddefinitions $end
#0
$dumpvars
bx '
bx &
bx %
0$
0#
bx "
bx !
$end
#1000
1$
1#
#2000
0$
0#
#3000
b0 "
b0 %
1#
#4000
b1 "
b1 %
0#
#5000
b10001111 !
b10001111 &
b10001111000000000000000000000000 '
b10 "
b10 %
1#
#6000
b11 "
b11 %
0#
#7000
b100 "
b100 %
1#
#8000
0#
#9000
b11010110 !
b11010110 &
b11010110000000000000000000000000 '
1#
